llama_index/packs/tables/__init__.py
llama_index/packs/tables/chain_of_table/__init__.py
llama_index/packs/tables/chain_of_table/base.py
llama_index/packs/tables/mix_self_consistency/__init__.py
llama_index/packs/tables/mix_self_consistency/base.py
llama_index_packs_tables-0.3.1.dist-info/METADATA
llama_index_packs_tables-0.3.1.dist-info/WHEEL
llama_index_packs_tables-0.3.1.dist-info/licenses/LICENSE
llama_index_packs_tables-0.3.1.dist-info/RECORD
