Metadata-Version: 2.4
Name: llama-index-packs-tables
Version: 0.3.1
Summary: llama-index packs tables integration
Author-email: Your Name <you@example.com>
Maintainer: Disiok, jerryjliu
License-Expression: MIT
License-File: LICENSE
Keywords: chain,dataframe,pandas,table,tables
Requires-Python: <4.0,>=3.9
Requires-Dist: llama-index-core<0.13,>=0.12.0
Requires-Dist: llama-index-llms-openai<0.5,>=0.4.0
Requires-Dist: pandas
